{"files":{"xmlui/dist/standalone/xmlui-standalone.umd.js.map":{"size":13640799,"mtime_nanos":1779368856181019484,"mode":420,"is_dir":false},"xmlui/.turbo/turbo-build$colon$xmlui-standalone.log":{"size":7491,"mtime_nanos":1779368860456038667,"mode":420,"is_dir":false},"xmlui/dist/standalone":{"size":0,"mtime_nanos":0,"mode":0,"is_dir":true},"xmlui/dist/standalone/xmlui-standalone.umd.js":{"size":4917326,"mtime_nanos":1779368856177019467,"mode":420,"is_dir":false},"xmlui/dist/standalone/xmlui.d.ts":{"size":144825,"mtime_nanos":1779368859896036156,"mode":420,"is_dir":false}},"order":["xmlui/.turbo/turbo-build$colon$xmlui-standalone.log","xmlui/dist/standalone","xmlui/dist/standalone/xmlui-standalone.umd.js","xmlui/dist/standalone/xmlui-standalone.umd.js.map","xmlui/dist/standalone/xmlui.d.ts"]}