[
  {
    "tag_name": "xmlui@0.10.10",
    "published_at": "2025-09-09T12:43:31Z",
    "changes": [
      {
        "description": "Bump package version",
        "commit_sha": "fff80c5"
      }
    ],
    "assets": [
      {
        "name": "xmlui-0.10.10.js",
        "browser_download_url": "https://github.com/xmlui-org/xmlui/releases/download/xmlui%400.10.10/xmlui-0.10.10.js"
      }
    ]
  },
  {
    "tag_name": "xmlui@0.10.8",
    "published_at": "2025-09-04T13:13:38Z",
    "changes": [
      {
        "description": "Add experimental Timer component",
        "commit_sha": "a4d62c4"
      },
      {
        "description": "Add the appendBlob function to the ApiInterceptor backend",
        "commit_sha": "7ed2918"
      }
    ],
    "assets": [
      {
        "name": "xmlui-0.10.8.js",
        "browser_download_url": "https://github.com/xmlui-org/xmlui/releases/download/xmlui%400.10.8/xmlui-0.10.8.js"
      }
    ]
  },
  {
    "tag_name": "xmlui@0.10.7",
    "published_at": "2025-09-03T10:53:53Z",
    "changes": [
      {
        "description": "Fixed BarChart hideTickY property to not remove the Y axis when set to true.",
        "commit_sha": "664ea4f"
      },
      {
        "description": "Fixed Checkbox and Switch visual issue. Fixed Line- and BarChart visual glitch in Table.",
        "commit_sha": "a739a26"
      },
      {
        "description": "Small fixes for tiny bugs found during MyWorkDrive update",
        "commit_sha": "bdb54dd"
      },
      {
        "description": "Fixed BarChart tick labels not appearing.",
        "commit_sha": "81724c6"
      }
    ],
    "assets": [
      {
        "name": "xmlui-0.10.7.js",
        "browser_download_url": "https://github.com/xmlui-org/xmlui/releases/download/xmlui%400.10.7/xmlui-0.10.7.js"
      }
    ]
  },
  {
    "tag_name": "xmlui@0.10.6",
    "published_at": "2025-09-02T08:34:14Z",
    "changes": [
      {
        "description": "fix ssr",
        "commit_sha": "6464ec8"
      }
    ],
    "assets": [
      {
        "name": "xmlui-0.10.6.js",
        "browser_download_url": "https://github.com/xmlui-org/xmlui/releases/download/xmlui%400.10.6/xmlui-0.10.6.js"
      }
    ]
  },
  {
    "tag_name": "xmlui@0.10.5",
    "published_at": "2025-09-02T07:46:45Z",
    "changes": [
      {
        "description": "fix missing dependency",
        "commit_sha": "d38351d"
      }
    ],
    "assets": [
      {
        "name": "xmlui-0.10.5.js",
        "browser_download_url": "https://github.com/xmlui-org/xmlui/releases/download/xmlui%400.10.5/xmlui-0.10.5.js"
      }
    ]
  },
  {
    "tag_name": "xmlui@0.10.4",
    "published_at": "2025-09-01T15:53:19Z",
    "changes": [
      {
        "description": "small fixes: Avatar, FileUploadDropzone, auto xsrf token handling",
        "commit_sha": "43fd8c5"
      },
      {
        "description": "Autocomplete: initiallyOpen prop",
        "commit_sha": "1df8e5d"
      },
      {
        "description": "Reworked Pagination layout strategy. Provided props to better control layout: pageSizeSelectorPosition, pageInfoPosition, buttonRowPosition. These props are available in Table pagination as well.",
        "commit_sha": "0d5d9d1"
      },
      {
        "description": "DropdownMenu doesn't cooperate with Fragment triggerTemplate",
        "commit_sha": "3def673"
      },
      {
        "description": "include themes.scss file in lib dist",
        "commit_sha": "428ebea"
      },
      {
        "description": "FileUploadDropZone fixes (dropPlaceholder disappeared)",
        "commit_sha": "a12ce66"
      }
    ],
    "assets": [
      {
        "name": "xmlui-0.10.4.js",
        "browser_download_url": "https://github.com/xmlui-org/xmlui/releases/download/xmlui%400.10.4/xmlui-0.10.4.js"
      }
    ]
  },
  {
    "tag_name": "xmlui@0.10.3",
    "published_at": "2025-08-29T12:38:27Z",
    "changes": [
      {
        "description": "Add solid overflow handling modes to Text",
        "commit_sha": "2e512bb"
      },
      {
        "description": "Remove the \"codefence\" Text variant",
        "commit_sha": "46d1d18"
      },
      {
        "description": "feat: support aligning cells in a Table row vertically",
        "commit_sha": "6bc9ed1"
      },
      {
        "description": "Add new, compound layout property name parsing",
        "commit_sha": "0b1f983"
      },
      {
        "description": "Text is displayed as inline (you can nest Text into Text)",
        "commit_sha": "a2637f3"
      },
      {
        "description": "Adding the \"part\" concept to native components",
        "commit_sha": "eb4d592"
      }
    ],
    "assets": [
      {
        "name": "xmlui-0.10.3.js",
        "browser_download_url": "https://github.com/xmlui-org/xmlui/releases/download/xmlui%400.10.3/xmlui-0.10.3.js"
      }
    ]
  },
  {
    "tag_name": "xmlui@0.10.2",
    "published_at": "2025-08-26T14:36:22Z",
    "changes": [
      {
        "description": "fix: LineChart - sizing issue",
        "commit_sha": "ff14e15"
      },
      {
        "description": "feat: make input padding configurable via theme variables",
        "commit_sha": "1451a94"
      }
    ],
    "assets": [
      {
        "name": "xmlui-0.10.2.js",
        "browser_download_url": "https://github.com/xmlui-org/xmlui/releases/download/xmlui%400.10.2/xmlui-0.10.2.js"
      }
    ]
  },
  {
    "tag_name": "xmlui@0.10.1",
    "published_at": "2025-08-21T12:44:50Z",
    "changes": [
      {
        "description": "Refactor visual components to allow tooltip",
        "commit_sha": "442416b"
      },
      {
        "description": "feat: add custom tooltip template support for Bar and Line charts",
        "commit_sha": "a018431"
      },
      {
        "description": "Pagination component now handles itemCount being undefined/null. Introduced hasPrevPage and hasNextPage props to toggle button disabled state.",
        "commit_sha": "33cb547"
      },
      {
        "description": "Enhance the disabledDates property of DatePicker",
        "commit_sha": "b5d7537"
      }
    ],
    "assets": [
      {
        "name": "xmlui-0.10.1.js",
        "browser_download_url": "https://github.com/xmlui-org/xmlui/releases/download/xmlui%400.10.1/xmlui-0.10.1.js"
      }
    ]
  },
  {
    "tag_name": "xmlui@0.10.0",
    "published_at": "2025-08-19T12:16:45Z",
    "changes": [
      {
        "description": "Add tooltip behavior to visible components",
        "commit_sha": "000a311"
      },
      {
        "description": "Rework inline styling system, prepare for responsive styling",
        "commit_sha": "eb8b958"
      },
      {
        "description": "Added features to the Pagination component: page size selector dropdown control. Also added the following props: layout orientation and layout order reversal.",
        "commit_sha": "6d0ce52"
      },
      {
        "description": "feat: add theme variable support for LineChart stroke width",
        "commit_sha": "8c98f33"
      },
      {
        "description": "feat: add didChange event handler to Tabs component",
        "commit_sha": "ef86593"
      },
      {
        "description": "test: create e2e tests for chart components",
        "commit_sha": "da5f4e7"
      },
      {
        "description": "Integrated the new Pagination component with Table.",
        "commit_sha": "47c7a2d"
      },
      {
        "description": "Add \"activated\" event to TabItem",
        "commit_sha": "740f904"
      },
      {
        "description": "Add \"parts\" to component metadata",
        "commit_sha": "5009c52"
      },
      {
        "description": "Remove \"from\" from the list or reserved script keywords, as no longer used",
        "commit_sha": "2f5ec32"
      }
    ],
    "assets": [
      {
        "name": "xmlui-0.10.0.js",
        "browser_download_url": "https://github.com/xmlui-org/xmlui/releases/download/xmlui%400.10.0/xmlui-0.10.0.js"
      }
    ]
  }
]